{
  "players": [
    {
      "id": "player-1a2b3c4d",
      "name": "Трихук Никита",
      "team": "Bulldogs",
      "photo": "21",
      "height": 187,
      "games": 0,
      "points": 0,
      "rebounds": 0,
      "assists": 0,
      "blocks": 0,
      "plusMinus": 0,
      "efficiency": 0
    },
    {
      "id": "player-2b3c4d5e",
      "name": "Чугунов Макар",
      "team": "Bulldogs",
      "photo": "24",
      "height": 187,
      "games": 0,
      "points": 0,
      "rebounds": 0,
      "assists": 0,
      "blocks": 0,
      "plusMinus": 0,
      "efficiency": 0
    },
    {
      "id": "player-3c4d5e6f",
      "name": "Шипко Владимир",
      "team": "Bulldogs",
      "photo": "5",
      "height": 175,
      "games": 0,
      "points": 0,
      "rebounds": 0,
      "assists": 0,
      "blocks": 0,
      "plusMinus": 0,
      "efficiency": 0
    },
    {
      "id": "player-4d5e6f7g",
      "name": "Яртым Андрей",
      "team": "Bulldogs",
      "photo": "26",
      "height": 174,
      "games": 0,
      "points": 0,
      "rebounds": 0,
      "assists": 0,
      "blocks": 0,
      "plusMinus": 0,
      "efficiency": 0
    },
    {
      "id": "player-5e6f7g8h",
      "name": "Макаров Николай",
      "team": "Bulldogs",
      "photo": "25",
      "height": 176,
      "games": 0,
      "points": 0,
      "rebounds": 0,
      "assists": 0,
      "blocks": 0,
      "plusMinus": 0,
      "efficiency": 0
    }
  ]
}
